graspnetAPI/__init__.py
graspnetAPI/grasp.py
graspnetAPI/graspnet.py
graspnetAPI/graspnet_eval.py
graspnetAPI/utils/__init__.py
graspnetAPI/utils/config.py
graspnetAPI/utils/eval_utils.py
graspnetAPI/utils/pose.py
graspnetAPI/utils/rotation.py
graspnetAPI/utils/trans3d.py
graspnetAPI/utils/utils.py
graspnetAPI/utils/vis.py
graspnetAPI/utils/xmlhandler.py
graspnetAPI/utils/dexnet/__init__.py
graspnetAPI/utils/dexnet/abstractstatic.py
graspnetAPI/utils/dexnet/constants.py
graspnetAPI/utils/dexnet/grasping/__init__.py
graspnetAPI/utils/dexnet/grasping/contacts.py
graspnetAPI/utils/dexnet/grasping/grasp.py
graspnetAPI/utils/dexnet/grasping/grasp_quality_config.py
graspnetAPI/utils/dexnet/grasping/grasp_quality_function.py
graspnetAPI/utils/dexnet/grasping/graspable_object.py
graspnetAPI/utils/dexnet/grasping/quality.py
graspnetAPI/utils/dexnet/grasping/meshpy/__init__.py
graspnetAPI/utils/dexnet/grasping/meshpy/mesh.py
graspnetAPI/utils/dexnet/grasping/meshpy/obj_file.py
graspnetAPI/utils/dexnet/grasping/meshpy/sdf.py
graspnetAPI/utils/dexnet/grasping/meshpy/sdf_file.py
graspnetAPI/utils/dexnet/grasping/meshpy/stable_pose.py
graspnetAPI-1.2.9.dist-info/METADATA
graspnetAPI-1.2.9.dist-info/WHEEL
graspnetAPI-1.2.9.dist-info/top_level.txt
graspnetAPI-1.2.9.dist-info/RECORD
