Metadata-Version: 2.1
Name: graspnetAPI
Version: 1.2.9
Summary: graspnet API
Home-page: https://graspnet.net
Author: Hao-Shu Fang, Chenxi Wang, Minghao Gou
Author-email: gouminghao@gmail.com
License: UNKNOWN
Platform: UNKNOWN
Requires-Dist: numpy
Requires-Dist: scipy
Requires-Dist: transforms3d (==0.3.1)
Requires-Dist: open3d (>=0.8.0.0)
Requires-Dist: trimesh
Requires-Dist: tqdm
Requires-Dist: Pillow
Requires-Dist: opencv-python
Requires-Dist: pillow
Requires-Dist: matplotlib
Requires-Dist: pywavefront
Requires-Dist: scikit-image
Requires-Dist: autolab-core
Requires-Dist: autolab-perception
Requires-Dist: cvxopt
Requires-Dist: dill
Requires-Dist: h5py
Requires-Dist: sklearn
Requires-Dist: grasp-nms
